setup.cfg
setup.py
ifilter/__init__.py
ifilter.egg-info/PKG-INFO
ifilter.egg-info/SOURCES.txt
ifilter.egg-info/dependency_links.txt
ifilter.egg-info/entry_points.txt
ifilter.egg-info/top_level.txt