Metadata-Version: 1.1
Name: ifilter
Version: 0.2
Summary: ifilter is a command line tool for interactive filtering of pipes.
Home-page: https://github.com/stefan-hudelmaier/ifilter
Author: Stefan Hudelmaier
Author-email: hudelmaier@gmail.com
License: UNKNOWN
Download-URL: https://github.com/stefan-hudelmaier/ifilter/tarball/0.2
Keywords: shell,pipe,filter,interactive
Platform: UNKNOWN
Classifier: Development Status :: 4 - Beta
Classifier: Environment :: Console
Classifier: Intended Audience :: Developers
Classifier: Intended Audience :: System Administrators
Classifier: Operating System :: Unix
Classifier: Operating System :: POSIX
Classifier: Programming Language :: Python
Classifier: Programming Language :: Python :: 2.5
Classifier: Programming Language :: Python :: 2.6
Classifier: Programming Language :: Python :: 2.7
Classifier: Topic :: System :: Systems Administration
